backend/__init__.py
backend/build_binary.py
backend/cli.py
backend/main.py
frontend/dist/index.html
frontend/dist/assets/__vite-browser-external-BIHI7g3E.js
frontend/dist/assets/index-B5LQyS6I.css
frontend/dist/assets/index-o0SFcEJo.js
frontend/dist/assets/pdf.worker.min-GB3t0DcA.mjs
frontend/dist/icon/macos/icon.icns
frontend/dist/icon/png/1024x1024.png
frontend/dist/icon/png/64x64.png
frontend/dist/icon/win/icon.ico
deepread-0.0.3.dist-info/METADATA
deepread-0.0.3.dist-info/WHEEL
deepread-0.0.3.dist-info/entry_points.txt
deepread-0.0.3.dist-info/top_level.txt
deepread-0.0.3.dist-info/RECORD
