Metadata-Version: 2.2
Name: deepread
Version: 0.0.3
Summary: A PDF reading and analysis application
Author-email: Ngoc Khuat <qn.khuat@gmail.com>
Project-URL: Homepage, https://github.com/qnkhuat/deepread
Classifier: Development Status :: 4 - Beta
Classifier: Intended Audience :: End Users/Desktop
Classifier: License :: OSI Approved :: MIT License
Classifier: Programming Language :: Python :: 3.10
Classifier: Programming Language :: Python :: 3.11
Classifier: Programming Language :: Python :: 3.12
Requires-Python: >=3.10
Requires-Dist: fastapi[standard]==0.115.8
Requires-Dist: openai==1.65.2
Requires-Dist: pymupdf==1.24.11
Requires-Dist: pymupdf4llm==0.0.17
